{"urls": [
{"url": "http://饭太硬.top/tv","name":"饭太硬线路"},
{"url": "https://mirror.ghproxy.com/raw.githubusercontent.com/PizazzGY/TVBox/main/api.json","name":"潇洒GY线路"},
{"url": "https://pastebin.com/raw/5NHaxyGR","name":"道长线路"},
{"url": "http://xhww.fun:63/小米/DEMO.json","name":"小米线路"},
{"url": "https://xhdwc.tk/0","name":"dsawi0线路"},
{"url": "https://mirror.ghproxy.com/raw.githubusercontent.com/xmbjm/xmbjmjk/main/xmbjm.json","name":"拾光线路"},
{"url": "https://jihulab.com/yw88075/tvbox/-/raw/main/dr/js.json","name":"心魔线路"},
{"url": "https://agit.ai/Yoursmile7/TVBox/raw/branch/master/XC.json","name":"南风线路"},
{"url": "http://itvbox.cc/tvbox/云星日记/1.m3u8","name":"云星日记"},
{"url": "http://8.210.232.168/xc.json","name":"星辰线路"},
{"url": "https://ysys.lic10.cn/ys/ysys.json","name":"余生线路"},
{"url": "https://jihulab.com/clear1/yingmi/-/raw/main/xh.txt","name":"影迷线路"},
{"url": "https://agit.ai/n/b/raw/branch/a/b/c.json","name":"agit/abc线路"},
{"url": "https://szyyds.cn/tv/x.json","name":"小马线路"},
{"url": "http://rihou.vip:88/荷城茶秀","name":"荷城线路"}

]
}
